spexxy/__init__.py
spexxy/application.py
spexxy/cli/__init__.py
spexxy/cli/spexxy.py
spexxy/cli/spexxytools.py
spexxy/component/__init__.py
spexxy/component/component.py
spexxy/component/grid.py
spexxy/component/spectrumcomponent.py
spexxy/component/star.py
spexxy/component/tellurics.py
spexxy/data/__init__.py
spexxy/data/filter.py
spexxy/data/fitsspectrum.py
spexxy/data/isochrone.py
spexxy/data/losvd.py
spexxy/data/lsf.py
spexxy/data/resultsfits.py
spexxy/data/spectrum.py
spexxy/data/vega.sed
spexxy/grid/__init__.py
spexxy/grid/ferre.py
spexxy/grid/files.py
spexxy/grid/fits.py
spexxy/grid/grid.py
spexxy/grid/sub.py
spexxy/grid/synspec.py
spexxy/grid/values.py
spexxy/init/__init__.py
spexxy/init/fromcsv.py
spexxy/init/frompath.py
spexxy/init/fromvalues.py
spexxy/init/fromvhelio.py
spexxy/init/fromyaml.py
spexxy/init/init.py
spexxy/interpolator/__init__.py
spexxy/interpolator/interpolator.py
spexxy/interpolator/linear.py
spexxy/interpolator/spline.py
spexxy/interpolator/sub.py
spexxy/interpolator/tellurics.py
spexxy/interpolator/ulyss.py
spexxy/main/__init__.py
spexxy/main/base.py
spexxy/main/fromgrid.py
spexxy/main/lincomb.py
spexxy/main/multimain.py
spexxy/main/paramsfit.py
spexxy/mask/__init__.py
spexxy/mask/ends.py
spexxy/mask/frompath.py
spexxy/mask/mask.py
spexxy/mask/negative.py
spexxy/mask/ranges.py
spexxy/object.py
spexxy/tools/__init__.py
spexxy/tools/filters/__init__.py
spexxy/tools/filters/limbdark.py
spexxy/tools/grid/2ndderivs.py
spexxy/tools/grid/__init__.py
spexxy/tools/grid/combine.py
spexxy/tools/grid/convert.py
spexxy/tools/grid/convolve.py
spexxy/tools/grid/create.py
spexxy/tools/grid/fillholes.py
spexxy/tools/grid/findholes.py
spexxy/tools/grid/info.py
spexxy/tools/grid/resample.py
spexxy/tools/isochrone/__init__.py
spexxy/tools/isochrone/apply.py
spexxy/tools/isochrone/cut.py
spexxy/tools/isochrone/interpolate.py
spexxy/tools/lsf/__init__.py
spexxy/tools/lsf/apply.py
spexxy/tools/plot.py
spexxy/tools/spectrum/__init__.py
spexxy-2.9.1.dist-info/LICENSE
spexxy-2.9.1.dist-info/METADATA
spexxy-2.9.1.dist-info/WHEEL
spexxy-2.9.1.dist-info/entry_points.txt
spexxy-2.9.1.dist-info/RECORD
