Metadata-Version: 2.1
Name: spexxy
Version: 2.9.1
Summary: spectrum fitting package
License: MIT
Author: Tim-Oliver Husser
Author-email: thusser@uni-goettingen.de
Requires-Python: >=3.9,<3.13
Classifier: License :: OSI Approved :: MIT License
Classifier: Programming Language :: Python :: 3
Classifier: Programming Language :: Python :: 3.9
Classifier: Programming Language :: Python :: 3.10
Classifier: Programming Language :: Python :: 3.11
Classifier: Programming Language :: Python :: 3.12
Requires-Dist: astropy (>=6.0,<7.0)
Requires-Dist: h5py (>=3.11.0,<4.0.0)
Requires-Dist: lmfit (>=1.3.1,<2.0.0)
Requires-Dist: matplotlib (>=3.9.1,<4.0.0)
Requires-Dist: numpy (>=1.26.4,<2.0.0)
Requires-Dist: pandas (>=2.2.2,<3.0.0)
Requires-Dist: pyqt5 (>=5.15.10,<6.0.0)
Requires-Dist: pyyaml (>=6.0.1,<7.0.0)
Requires-Dist: scipy (>=1.13,<2.0)
Requires-Dist: single-source (>=0.4.0,<0.5.0)
